metrics_miscellany/GMM_class.py
metrics_miscellany/__init__.py
metrics_miscellany/datamat-.py
metrics_miscellany/datamat.py
metrics_miscellany/estimators.py
metrics_miscellany/gmm.py
metrics_miscellany/kernel_methods.py
metrics_miscellany/order_statistics.py
metrics_miscellany/random.py
metrics_miscellany/test_statistics.py
metrics_miscellany/tests.py
metrics_miscellany/utils.py
Metrics_Miscellany-0.2.5.dist-info/LICENSE.txt
Metrics_Miscellany-0.2.5.dist-info/METADATA
Metrics_Miscellany-0.2.5.dist-info/WHEEL
Metrics_Miscellany-0.2.5.dist-info/top_level.txt
Metrics_Miscellany-0.2.5.dist-info/RECORD
