Metadata-Version: 2.1
Name: Metrics-Miscellany
Version: 0.2.5
Summary: Miscellaneous code for estimation involving pandas dataframes.
Home-page: https://bitbucket.org/ligonresearch/metrics_miscellany
Author: Ethan Ligon
Author-email: ligon@berkeley.edu
License: Creative Commons Attribution-Noncommercial-ShareAlike 4.0 International license
License-File: LICENSE.txt
